opvoeden_api/__init__.py
opvoeden_api/article_utils.py
opvoeden_api/client.py
opvoeden_api/models.py
opvoeden_api_client-2.1.0.dist-info/DESCRIPTION.rst
opvoeden_api_client-2.1.0.dist-info/METADATA
opvoeden_api_client-2.1.0.dist-info/RECORD
opvoeden_api_client-2.1.0.dist-info/WHEEL
opvoeden_api_client-2.1.0.dist-info/metadata.json
opvoeden_api_client-2.1.0.dist-info/top_level.txt
