Metadata-Version: 2.0
Name: opvoeden-api-client
Version: 2.1.0
Summary: Client for Stichting Opvoeden API V2
Home-page: https://github.com/leukeleu/opvoeden-api-client
Author: Leukeleu
Author-email: info@leukeleu.nl
License: MIT
Keywords: stichting,opvoeden,api,client,rest
Platform: UNKNOWN
Classifier: Intended Audience :: Developers
Classifier: License :: OSI Approved :: MIT License
Classifier: Operating System :: OS Independent
Classifier: Programming Language :: Python
Classifier: Programming Language :: Python :: 2.7
Classifier: Programming Language :: Python :: 3.4
Classifier: Programming Language :: Python :: 3.5
Requires-Dist: requests
